prqlc-0.13.10.dist-info/METADATA
prqlc-0.13.10.dist-info/WHEEL
prqlc/__init__.py
prqlc/__init__.pyi
prqlc/debug.pyi
prqlc/prqlc.abi3.so
prqlc/py.typed
prqlc-0.13.10.dist-info/RECORD
