Metadata-Version: 2.4
Name: prqlc
Version: 0.13.10
Classifier: Programming Language :: Rust
Classifier: Programming Language :: Python :: Implementation :: CPython
Classifier: Programming Language :: Python :: Implementation :: PyPy
Summary: Python bindings for prqlc, the PRQL compiler
Requires-Python: >=3.9
